README.txt
setup.py
redirector/__init__.py
redirector/factory.py
redirector/redirector.py
redirector/redirectors.py
redirector.egg-info/PKG-INFO
redirector.egg-info/SOURCES.txt
redirector.egg-info/dependency_links.txt
redirector.egg-info/entry_points.txt
redirector.egg-info/not-zip-safe
redirector.egg-info/requires.txt
redirector.egg-info/top_level.txt