Metadata-Version: 1.0
Name: redirector
Version: 0.1.1
Summary: WSGI middleware/app for managing redirects
Home-page: http://k0s.org/hg/redirector
Author: Jeff Hammel
Author-email: k0scist@gmail.com
License: GPL
Platform: UNKNOWN
